{
   "Author of this method": "Alailson Barbosa Ribeiro <ribeiro@alailson.com.br> (c)2020",
   "Spanish (Panama)": "",
   "es_PA": "",
   "es-PA": "",
   "LocalSets": {
      "code": "es_PA",
      "ietf": "es-PA",
      "name": "Spanish (Panama)",
      "language_name": "",
      "language_code": null,
      "language_flag": "pa",
      "iso": "PA",
      "iso3": "PAN",
      "country": "PANAMA",
      "country_code": "591",
      "country_name": "Panama",
      "languages": "es-PA,en",
      "is_eu": "0",
      "phone_code": "507",
      "currency": "Balboa",
      "currency_code": "PAB",
      "currency_symbol": "B/.",
      "population": "3410676",
      "fips_code": "PM",
      "north": "9.6474132494631",
      "south": "7.20236920646422",
      "east": "-77.1563637579897",
      "west": "-83.0523988577088",
      "capital": "Panama City",
      "continent": "NA",
      "continent_name": "North America",
      "area_km2": "78200",
      "geo_name": "PAN"
   },
   "To translate include lines like these in this file in your language": "",
   "in english here": "in your language here",
   "": "",
   "Country Panama": "Country Panama"
}